pelican_shiori/__init__.py
pelican_shiori/static/css/custom-scss.scss
pelican_shiori/static/css/pygments-tomorrow.scss
pelican_shiori/static/css/shiori.scss
pelican_shiori/static/css/bootstrap-sass/_bootstrap-compass.scss
pelican_shiori/static/css/bootstrap-sass/_bootstrap-mincer.scss
pelican_shiori/static/css/bootstrap-sass/_bootstrap-sprockets.scss
pelican_shiori/static/css/bootstrap-sass/bootstrap.scss
pelican_shiori/static/css/bootstrap-sass/bootstrap/_alerts.scss
pelican_shiori/static/css/bootstrap-sass/bootstrap/_badges.scss
pelican_shiori/static/css/bootstrap-sass/bootstrap/_breadcrumbs.scss
pelican_shiori/static/css/bootstrap-sass/bootstrap/_button-groups.scss
pelican_shiori/static/css/bootstrap-sass/bootstrap/_buttons.scss
pelican_shiori/static/css/bootstrap-sass/bootstrap/_carousel.scss
pelican_shiori/static/css/bootstrap-sass/bootstrap/_close.scss
pelican_shiori/static/css/bootstrap-sass/bootstrap/_code.scss
pelican_shiori/static/css/bootstrap-sass/bootstrap/_component-animations.scss
pelican_shiori/static/css/bootstrap-sass/bootstrap/_dropdowns.scss
pelican_shiori/static/css/bootstrap-sass/bootstrap/_forms.scss
pelican_shiori/static/css/bootstrap-sass/bootstrap/_glyphicons.scss
pelican_shiori/static/css/bootstrap-sass/bootstrap/_grid.scss
pelican_shiori/static/css/bootstrap-sass/bootstrap/_input-groups.scss
pelican_shiori/static/css/bootstrap-sass/bootstrap/_jumbotron.scss
pelican_shiori/static/css/bootstrap-sass/bootstrap/_labels.scss
pelican_shiori/static/css/bootstrap-sass/bootstrap/_list-group.scss
pelican_shiori/static/css/bootstrap-sass/bootstrap/_media.scss
pelican_shiori/static/css/bootstrap-sass/bootstrap/_mixins.scss
pelican_shiori/static/css/bootstrap-sass/bootstrap/_modals.scss
pelican_shiori/static/css/bootstrap-sass/bootstrap/_navbar.scss
pelican_shiori/static/css/bootstrap-sass/bootstrap/_navs.scss
pelican_shiori/static/css/bootstrap-sass/bootstrap/_normalize.scss
pelican_shiori-0.2.1.dist-info/DESCRIPTION.rst
pelican_shiori-0.2.1.dist-info/LICENSE.txt
pelican_shiori-0.2.1.dist-info/METADATA
pelican_shiori-0.2.1.dist-info/RECORD
pelican_shiori-0.2.1.dist-info/WHEEL
pelican_shiori-0.2.1.dist-info/metadata.json
pelican_shiori-0.2.1.dist-info/top_level.txt
