Metadata-Version: 2.0
Name: pelican-shiori
Version: 0.2.1
Summary: Shiori theme for Pelican
Home-page: https://github.com/siddhantgoel/pelican-shiori
Author: Siddhant Goel
Author-email: siddhantgoel@gmail.com
License: MIT
Keywords: python pelican pelican-theme static-site
Platform: UNKNOWN
Classifier: Development Status :: 4 - Beta
Classifier: Framework :: Pelican :: Themes
Classifier: License :: OSI Approved :: MIT License
Classifier: Programming Language :: Python :: 3
Classifier: Programming Language :: Python :: 3.3
Classifier: Programming Language :: Python :: 3.4
Classifier: Programming Language :: Python :: 3.5
Classifier: Programming Language :: Python :: 3.6
Requires-Dist: cssmin
Requires-Dist: jinja2
Requires-Dist: webassets
